jcvt/__init__.py
jcvt/converter.py
jcvt-0.1.0.dist-info/LICENSE
jcvt-0.1.0.dist-info/METADATA
jcvt-0.1.0.dist-info/WHEEL
jcvt-0.1.0.dist-info/top_level.txt
jcvt-0.1.0.dist-info/RECORD
